millipede/__init__.py
millipede/binomial.py
millipede/containers.py
millipede/normal.py
millipede/sampler.py
millipede/selection.py
millipede/util.py
millipede_regression-0.1.7.dist-info/LICENSE
millipede_regression-0.1.7.dist-info/METADATA
millipede_regression-0.1.7.dist-info/WHEEL
millipede_regression-0.1.7.dist-info/top_level.txt
millipede_regression-0.1.7.dist-info/RECORD
