Metadata-Version: 2.1
Name: millipede-regression
Version: 0.1.7
Summary: A library for bayesian variable selection
Home-page: https://github.com/BasisResearch/millipede
Author: Martin Jankowiak
Author-email: mjankowi@broadinstitute.org
License: Apache 2.0
Keywords: bayesian variable selection
Classifier: Intended Audience :: Developers
Classifier: Intended Audience :: Science/Research
Classifier: License :: OSI Approved :: Apache Software License
Classifier: Operating System :: POSIX :: Linux
Classifier: Operating System :: MacOS :: MacOS X
Classifier: Programming Language :: Python :: 3.9
Requires-Python: >=3.8
License-File: LICENSE
Requires-Dist: torch
Requires-Dist: pandas
Requires-Dist: polyagamma ==1.3.5
Requires-Dist: tqdm
Provides-Extra: test
Requires-Dist: isort >=5.9 ; extra == 'test'
Requires-Dist: flake8 ; extra == 'test'
Requires-Dist: pytest >=5.0 ; extra == 'test'
